word_abbr/__init__.py
word_abbr/abbreviator.py
word_abbr/cli.py
word_abbr/data.py
word_abbr/data/abbreviations.json
word_abbr-0.1.1.dist-info/METADATA
word_abbr-0.1.1.dist-info/WHEEL
word_abbr-0.1.1.dist-info/entry_points.txt
word_abbr-0.1.1.dist-info/licenses/LICENSE
word_abbr-0.1.1.dist-info/RECORD
