Metadata-Version: 2.4
Name: word-abbr
Version: 0.1.1
Summary: A simple Python library for querying common abbreviations of English words.
Project-URL: Homepage, https://github.com/ethnjiang/word-abbr
Author-email: Ethan Jiang <ethn.jiang@gmail.com>
License-Expression: MIT
License-File: LICENSE
Classifier: License :: OSI Approved :: MIT License
Classifier: Programming Language :: Python :: 3
Requires-Python: >=3.8
Provides-Extra: dev
Requires-Dist: mypy; extra == 'dev'
Requires-Dist: pytest; extra == 'dev'
